{
  "id": "hin-050",
  "title": "यीशु को मैं सब कुछ देता, सब कुछ करता हूँ कुर्बान",
  "artist": "",
  "category": "hindi",
  "sections": [
    {
      "type": "verse",
      "label": "1",
      "lines": [
        "यीशु को मैं सब कुछ देता, सब कुछ करता हूँ कुर्बान",
        "जीऊंगा मैं रोज़ मसीह में, उस पर रखूंगा ईमान।"
      ]
    },
    {
      "type": "chorus",
      "label": "कोरस",
      "lines": [
        "सब मैं देता हूं, सब मैं देता हूं",
        "तुझी को मुबारक मुंजी, सब कुछ देता हूं।"
      ]
    },
    {
      "type": "verse",
      "label": "2",
      "lines": [
        "यीशु को मैं सब कुछ देता, झुकता तेरे कदमों पर",
        "छोड़ता सारी दुनियादारी, मुझे ले और अपना कर।"
      ]
    },
    {
      "type": "verse",
      "label": "3",
      "lines": [
        "यीशु को मैं सब कुछ देता, मुझे बिल्कुल अपना कर",
        "दे मकबूलियत की गवाही, हूं मैं तेरा सरासर।"
      ]
    },
    {
      "type": "verse",
      "label": "4",
      "lines": [
        "यीशु को मैं सब कुछ देता, अभी उसके पाक हुजूर",
        "मुझमें भर प्यार और कूवत, बरकतों से कर मामूर।"
      ]
    },
    {
      "type": "verse",
      "label": "5",
      "lines": [
        "यीशु को मैं सब कुछ देता, रुह की आग अब दिल में है",
        "आह! कमाल नजात की खुशी, सन्ना सन्ना उसकी जय।"
      ]
    }
  ]
}