{
  "id": "hin-099",
  "title": "मन का दीप जला, जीवन दीप जला",
  "artist": "",
  "category": "hindi",
  "sections": [
    {
      "type": "chorus",
      "label": "कोरस",
      "lines": [
        "मन का दीप जला, जीवन दीप जला,",
        "ख्वाबों में खोया है, जाग ज़रा मतवाले।"
      ]
    },
    {
      "type": "verse",
      "label": "1",
      "lines": [
        "सच बतलाओ तेरे मन में, रात ये कैसी छाई?",
        "अच्छा नहीं है देख संभल जा, यीशु से है जुदाई",
        "यीशु को अपना (2) ख्वाबों में .............."
      ]
    },
    {
      "type": "verse",
      "label": "2",
      "lines": [
        "यह दुनिया है ख्वाब सुनहरा, इसमें जो फंस जाए",
        "रोए तड़पे चैन न पाए, घुल-घुल कर मर जाए",
        "मन का मैल धुला (2) ख्वाबों में ................."
      ]
    },
    {
      "type": "verse",
      "label": "3",
      "lines": [
        "यीशु को तू अपने जीवन में, अपना मीत बना ले",
        "छोड़ दे अब यह दुनिया सुनहरी, दुनिया से मन फिरा ले",
        "होगा तेरा भला (2) ख्वाबों में .............."
      ]
    }
  ]
}