{
  "id": "hin-114",
  "title": "खुश हो, खुदावन्द आया है, उसको कबूल कर ले",
  "artist": "",
  "category": "hindi",
  "sections": [
    {
      "type": "verse",
      "label": "1",
      "lines": [
        "खुश हो, खुदावन्द आया है, उसको कबूल कर ले",
        "ऐ कुल जहां, हों हर एक दिल, मसीह को जगह दे।"
      ]
    },
    {
      "type": "verse",
      "label": "2",
      "lines": [
        "खुश हो मसीह अब बादशाह है, सब आदमी, हर जुबान",
        "समुन्दर भी, मैदान पहाड़, गीत गाएं खुश-इलहान।"
      ]
    },
    {
      "type": "verse",
      "label": "3",
      "lines": [
        "दुख और तकलीफ वह करता दूर, हटाता है गुनाह",
        "तारीकी में वह देता नूर, और बरकत बशा-बहा।"
      ]
    },
    {
      "type": "verse",
      "label": "4",
      "lines": [
        "रस्तबाज़ी और सच्चाई से, वह राज फैलाता है",
        "और अपनी कुल हुकूमत से, प्यार दिखाता है।"
      ]
    }
  ]
}