{
  "id": "hin-026",
  "title": "स्तुति प्रशंसा हे प्रभु",
  "artist": "",
  "category": "hindi",
  "sections": [
    {
      "type": "chorus",
      "label": "कोरस",
      "lines": [
        "स्तुति प्रशंसा हे प्रभु, मैं गाऊँ बार-बार",
        "महान उद्धार दे दिया, दिल शान्त कर दिया।"
      ]
    },
    {
      "type": "verse",
      "label": "1",
      "lines": [
        "संसार के फन्दे में था, पापों का दास था,",
        "लोहू की शक्ति से प्रभु, तूने छुड़ा लिया।"
      ]
    },
    {
      "type": "verse",
      "label": "2",
      "lines": [
        "पापों के भार से जीवन, मेरा दुखी हुआ,",
        "प्रभु ने बोझ उठा लिया, दुख दर्द सब हटा।"
      ]
    },
    {
      "type": "verse",
      "label": "3",
      "lines": [
        "अन्धेरा मन में था मेरे, पथ से भटक गया,",
        "उजियाला प्रभु बन गया, सत पथ दिखा दिया।"
      ]
    },
    {
      "type": "verse",
      "label": "4",
      "lines": [
        "घूरे के ढेर से प्रभु, तूने उठा लिया,",
        "फकीर और दरिद्र को, राजा बना दिया।"
      ]
    }
  ]
}